INSTALL
LICENSE
NOTICE
auth.dat
im_client.py
IM_client-1.8.0.data/scripts/im_client.py
imclient/__init__.py
imclient/imclient.py
IM_client-1.8.0.dist-info/LICENSE
IM_client-1.8.0.dist-info/METADATA
IM_client-1.8.0.dist-info/NOTICE
IM_client-1.8.0.dist-info/WHEEL
IM_client-1.8.0.dist-info/top_level.txt
IM_client-1.8.0.dist-info/RECORD
