Metadata-Version: 2.1
Name: IM-client
Version: 1.8.0
Summary: IM is a tool to manage virtual infrastructures on Cloud deployments
Home-page: http://www.grycap.upv.es/im
Author: GRyCAP - Universitat Politecnica de Valencia
Author-email: micafer1@upv.es
License: GPL version 3, http://www.gnu.org/licenses/gpl-3.0.txt
Platform: any
License-File: LICENSE
License-File: NOTICE
Requires-Dist: radl
Requires-Dist: netaddr
Requires-Dist: requests
